{
  "project_info": {
    "project_number": "436482266998",
    "firebase_url": "https://encuesta-e2431.firebaseio.com",
    "project_id": "encuesta-e2431",
    "storage_bucket": "encuesta-e2431.appspot.com"
  },
  "client": [
    {
      "client_info": {
        "mobilesdk_app_id": "1:436482266998:android:a1c160d98e346c669a0c57",
        "android_client_info": {
          "package_name": "com.project.encuesta"
        }
      },
      "oauth_client": [
        {
          "client_id": "436482266998-7iioph7gti0qr8up0v5i9bl63oiukbkt.apps.googleusercontent.com",
          "client_type": 1,
          "android_info": {
            "package_name": "com.project.encuesta",
            "certificate_hash": "932778480f72911262b7dacfb924f5a59c628832"
          }
        },
        {
          "client_id": "436482266998-qtvatdjk5a23opk5feubtum8ipdegtos.apps.googleusercontent.com",
          "client_type": 3
        }
      ],
      "api_key": [
        {
          "current_key": "AIzaSyAKvNgqwu86cbw69oO3s9qX3eg8S5509PA"
        }
      ],
      "services": {
        "appinvite_service": {
          "other_platform_oauth_client": [
            {
              "client_id": "436482266998-qtvatdjk5a23opk5feubtum8ipdegtos.apps.googleusercontent.com",
              "client_type": 3
            }
          ]
        }
      }
    }
  ],
  "configuration_version": "1"
}